rollbar_integration/__init__.py
rollbar_integration-0.0.2.dist-info/LICENSE
rollbar_integration-0.0.2.dist-info/METADATA
rollbar_integration-0.0.2.dist-info/WHEEL
rollbar_integration-0.0.2.dist-info/top_level.txt
rollbar_integration-0.0.2.dist-info/RECORD
