Metadata-Version: 2.1
Name: rollbar-integration
Version: 0.0.2
Summary: Rollbar integration for python tools
Author: Tom
License: UNKNOWN
Platform: UNKNOWN
Classifier: Programming Language :: Python :: 3
Classifier: License :: OSI Approved :: MIT License
Classifier: Operating System :: OS Independent
Requires-Python: >=3.6
License-File: LICENSE
Requires-Dist: rollbar
